<DockingManager>
    <ResizingPanel ResizeWidth="*" ResizeHeight="*" Orientation="Horizontal">
        <DockablePane ResizeWidth="200" ResizeHeight="*" Anchor="Left">
            <DockableContent Name="ICSharpCode_SharpDevelop_Project_ProjectBrowserPad" AutoHide="false" EffectiveSize="0,0" />
            <DockableContent Name="ICSharpCode_SharpDevelop_Gui_ToolsPad" AutoHide="false" EffectiveSize="0,0" />
        </DockablePane>
        <ResizingPanel ResizeWidth="*" ResizeHeight="*" Orientation="Vertical">
            <DocumentPanePlaceHolder />
            <DockablePane ResizeWidth="*" ResizeHeight="226" Anchor="Bottom">
                <DockableContent Name="ICSharpCode_SharpDevelop_Gui_ErrorListPad" AutoHide="false" FloatingWindowSize="1280,199" EffectiveSize="0,0" />
                <DockableContent Name="ICSharpCode_SharpDevelop_Gui_TaskListPad" AutoHide="false" FloatingWindowSize="1280,199" EffectiveSize="0,0" />
                <DockableContent Name="ICSharpCode_SharpDevelop_Gui_CompilerMessageView" AutoHide="false" FloatingWindowSize="1280,199" EffectiveSize="0,0" />
            </DockablePane>
        </ResizingPanel>
        <DockablePane ResizeWidth="200" ResizeHeight="*" Anchor="Right">
            <DockableContent Name="ICSharpCode_SharpDevelop_Gui_ClassBrowser_ClassBrowserPad" AutoHide="false" EffectiveSize="0,0" />
            <DockableContent Name="ICSharpCode_SharpDevelop_Gui_PropertyPad" AutoHide="false" EffectiveSize="0,0" />
        </DockablePane>
    </ResizingPanel>
    <Windows />
</DockingManager>